st_event_selection_interfaces/__init__.py
st_event_selection_interfaces/frontend/build/asset-manifest.json
st_event_selection_interfaces/frontend/build/bootstrap.min.css
st_event_selection_interfaces/frontend/build/index.html
st_event_selection_interfaces/frontend/build/precache-manifest.93b45ebf28a614f17430804535ae725a.js
st_event_selection_interfaces/frontend/build/service-worker.js
st_event_selection_interfaces/frontend/build/static/js/2.9848acac.chunk.js
st_event_selection_interfaces/frontend/build/static/js/2.9848acac.chunk.js.LICENSE.txt
st_event_selection_interfaces/frontend/build/static/js/2.9848acac.chunk.js.map
st_event_selection_interfaces/frontend/build/static/js/main.c5e881ee.chunk.js
st_event_selection_interfaces/frontend/build/static/js/main.c5e881ee.chunk.js.map
st_event_selection_interfaces/frontend/build/static/js/runtime-main.44d30fc2.js
st_event_selection_interfaces/frontend/build/static/js/runtime-main.44d30fc2.js.map
st_event_selection_interfaces-0.0.1.dist-info/LICENSE
st_event_selection_interfaces-0.0.1.dist-info/METADATA
st_event_selection_interfaces-0.0.1.dist-info/WHEEL
st_event_selection_interfaces-0.0.1.dist-info/top_level.txt
st_event_selection_interfaces-0.0.1.dist-info/RECORD
